iridescent_bg/__init__.py
iridescent_bg/generator.py
iridescent_bg-0.1.0.dist-info/licenses/LICENSE
iridescent_bg-0.1.0.dist-info/METADATA
iridescent_bg-0.1.0.dist-info/WHEEL
iridescent_bg-0.1.0.dist-info/top_level.txt
iridescent_bg-0.1.0.dist-info/RECORD
