Metadata-Version: 2.4
Name: iridescent-bg
Version: 0.1.0
Summary: A Python package to generate iridescent backgrounds with random colored lines and Gaussian blur.
Home-page: https://github.com/adams-charleen/iridescent-bg
Author: Charleen Adams
Author-email: cadams9@bidmc@harvard.edu
License: MIT
Classifier: Programming Language :: Python :: 3
Classifier: License :: OSI Approved :: MIT License
Classifier: Operating System :: OS Independent
Requires-Python: >=3.6
License-File: LICENSE
Requires-Dist: Pillow>=9.0.0
Requires-Dist: numpy>=1.20.0
Dynamic: author
Dynamic: author-email
Dynamic: classifier
Dynamic: description
Dynamic: description-content-type
Dynamic: home-page
Dynamic: license
Dynamic: license-file
Dynamic: requires-dist
Dynamic: requires-python
Dynamic: summary
